{
  "Umar": [
    {
      "filepath": "face_data\\Umar_20250604_004813.jpg",
      "timestamp": "20250604_004813"
    },
    {
      "filepath": "face_data\\Umar_20250604_004820.jpg",
      "timestamp": "20250604_004820"
    },
    {
      "filepath": "face_data\\Umar_20250604_004823.jpg",
      "timestamp": "20250604_004823"
    },
    {
      "filepath": "face_data\\Umar_20250604_004837.jpg",
      "timestamp": "20250604_004837"
    },
    {
      "filepath": "face_data\\Umar_20250604_004845.jpg",
      "timestamp": "20250604_004845"
    }
  ]
}